wrtest/__init__.py
wrtest-0.1.0.dist-info/METADATA
wrtest-0.1.0.dist-info/WHEEL
wrtest-0.1.0.dist-info/RECORD
